licor/__init__.py
licor/__main__.py
licor/comment.py
licor/filediscovery.py
licor/io.py
licor/main.py
licor/templates.py
licor/work.py
licor/templates/licenses_avail.json
licor/templates/a/AGPLv2.copyright.meta
licor/templates/a/AGPLv2.copyright.tx
licor/templates/a/AGPLv2.meta
licor/templates/a/AGPLv2.single-file.copyright.meta
licor/templates/a/AGPLv2.single-file.copyright.tx
licor/templates/a/AGPLv2.single-file.meta
licor/templates/a/AGPLv2.single-file.tx
licor/templates/a/AGPLv2.tx
licor/templates/a/AGPLv3.copyright.meta
licor/templates/a/AGPLv3.copyright.tx
licor/templates/a/AGPLv3.meta
licor/templates/a/AGPLv3.single-file.copyright.meta
licor/templates/a/AGPLv3.single-file.copyright.tx
licor/templates/a/AGPLv3.single-file.meta
licor/templates/a/AGPLv3.single-file.tx
licor/templates/a/AGPLv3.tx
licor/templates/g/GPLv2.copyright.meta
licor/templates/g/GPLv2.copyright.tx
licor/templates/g/GPLv2.meta
licor/templates/g/GPLv2.single-file.copyright.meta
licor/templates/g/GPLv2.single-file.copyright.tx
licor/templates/g/GPLv2.single-file.meta
licor/templates/g/GPLv2.single-file.tx
licor/templates/g/GPLv2.tx
licor/templates/g/GPLv3.copyright.meta
licor/templates/g/GPLv3.copyright.tx
licor/templates/g/GPLv3.meta
licor/templates/g/GPLv3.single-file.copyright.meta
licor/templates/g/GPLv3.single-file.copyright.tx
licor/templates/g/GPLv3.single-file.meta
licor/templates/g/GPLv3.single-file.tx
licor/templates/g/GPLv3.tx
licor/templates/l/LGPLv2.copyright.meta
licor/templates/l/LGPLv2.copyright.tx
licor/templates/l/LGPLv2.meta
licor/templates/l/LGPLv2.single-file.copyright.meta
licor/templates/l/LGPLv2.single-file.copyright.tx
licor/templates/l/LGPLv2.single-file.meta
licor/templates/l/LGPLv2.single-file.tx
licor/templates/l/LGPLv2.tx
licor/templates/l/LGPLv3.copyright.meta
licor/templates/l/LGPLv3.copyright.tx
licor/templates/l/LGPLv3.meta
licor/templates/l/LGPLv3.single-file.copyright.meta
licor-0.0.4.dist-info/DESCRIPTION.rst
licor-0.0.4.dist-info/METADATA
licor-0.0.4.dist-info/RECORD
licor-0.0.4.dist-info/WHEEL
licor-0.0.4.dist-info/entry_points.txt
licor-0.0.4.dist-info/metadata.json
licor-0.0.4.dist-info/top_level.txt
