Metadata-Version: 2.0
Name: licor
Version: 0.0.4
Summary: A script to add license disclaimers
Home-page: https://github.com/daknuett/licor
Author: Daniel Knüttel
Author-email: daniel.knuettel@daknuett.eu
License: UNKNOWN
Platform: UNKNOWN
Requires-Dist: docopt
